zalfmas_services/__init__.py
zalfmas_services/climate/__init__.py
zalfmas_services/climate/alter_time_series_wrapper.py
zalfmas_services/climate/csv_time_series_service.py
zalfmas_services/climate/csv_time_series_service_factory_service.py
zalfmas_services/climate/default_configs/__init__.py
zalfmas_services/climate/default_configs/dwd_germany_university_bonn_service.toml
zalfmas_services/climate/dwd_cmip_cordex_reklies_service.py
zalfmas_services/climate/dwd_core_ensemble_service.py
zalfmas_services/climate/dwd_germany_service.py
zalfmas_services/climate/dwd_germany_university_bonn_service.py
zalfmas_services/climate/isimip_3b_v1.1_service.py
zalfmas_services/climate/isimip_service.py
zalfmas_services/climate/klima_konform_service.py
zalfmas_services/climate/macsur_european_climate_scenarios_v2_service.py
zalfmas_services/climate/spreewasser_N_service.py
zalfmas_services/climate/test.toml
zalfmas_services/config/__init__.py
zalfmas_services/config/config_service.py
zalfmas_services/crop/__init__.py
zalfmas_services/crop/monica_crop_service.py
zalfmas_services/grid/__init__.py
zalfmas_services/grid/ascii_grid.py
zalfmas_services/grid/default_configs/ascii_grid.toml
zalfmas_services/jobs/__init__.py
zalfmas_services/jobs/jobs_service.py
zalfmas_services/management/__init__.py
zalfmas_services/management/fertilizer_service.py
zalfmas_services/management/ilr_sowing_harvest_dates.py
zalfmas_services/model/__init__.py
zalfmas_services/model/climate_algorithms.py
zalfmas_services/model/web-berest-datomic-dwd-import.py
zalfmas_services/registry_service.py
zalfmas_services/soil/__init__.py
zalfmas_services/soil/default_configs/sqlite_soil_data_service.toml
zalfmas_services/soil/global_soil_dataset.py
zalfmas_services/soil/sqlite_soil_data_service.py
zalfmas_services-0.1.13.dist-info/LICENSE
zalfmas_services-0.1.13.dist-info/METADATA
zalfmas_services-0.1.13.dist-info/WHEEL
zalfmas_services-0.1.13.dist-info/RECORD
