Metadata-Version: 2.3
Name: zalfmas-services
Version: 0.1.13
Summary: 
Author: Michael Berg-Mohnicke
Author-email: michael.berg@zalf.de
Requires-Python: >=3.10,<3.13
Classifier: Programming Language :: Python :: 3
Classifier: Programming Language :: Python :: 3.10
Classifier: Programming Language :: Python :: 3.11
Classifier: Programming Language :: Python :: 3.12
Requires-Dist: netcdf4 (>=1.7.2,<2.0.0)
Requires-Dist: numpy (>=2.1.2)
Requires-Dist: poetry-core (>=2.0.0)
Requires-Dist: pycapnp (>=2.0.0)
Requires-Dist: pyzmq (>=26.2.1)
Requires-Dist: tomli (>=2.0.1)
Requires-Dist: tomlkit (>=0.13.2)
Requires-Dist: zalfmas-capnp-schemas (>=0.1.33,<0.2.0)
Requires-Dist: zalfmas-common (>=0.1.29,<0.2.0)
